{"ID": {"Value": "PSR J1959+2048"}, "RAJ": {"Value": "19:59:36.76988", "Error": "5.00e-05", "Ref": "1994ApJ...426L..85A", "Flag": "0"}, "DECJ": {"Value": "+20:48:15.1222", "Error": "6.00e-04", "Ref": "1994ApJ...426L..85A", "Flag": "0"}, "P0": {"Value": "0.00160740168480632", "Error": "3.00e-17", "Ref": "1994ApJ...426L..85A", "Flag": "0"}, "P1": {"Value": "1.68515e-20", "Error": "9.00e-25", "Ref": "1994ApJ...426L..85A", "Flag": "0"}, "A1": {"Value": "0.0892253", "Error": "6e-7", "Ref": "1994ApJ...426L..85A", "Flag": "1"}, "F0": {"Value": "622.122030511927", "Error": "1.2e-11", "Ref": "1994ApJ...426L..85A", "Flag": "1"}, "F1": {"Value": "-6.522e-15", "Error": "4e-19", "Ref": "1994ApJ...426L..85A", "Flag": "1"}, "TASC": {"Value": "?", "Error": "?", "Ref": "?", "Flag": "0"}, "PB": {"Value": "0.3819666069", "Error": "8.00e-10", "Ref": "1994ApJ...426L..85A", "Flag": "0"}, "PBDOT": {"Value": "1.47e-11", "Error": "8.00e-13", "Ref": "1994ApJ...426L..85A", "Flag": "0"}, "Opt Mag": {"Value": "20-25(R)", "Error": "?", "Ref": "2006IAUS..230...55R", "Flag": "1"}, "K2": {"Value": "353", "Error": "4", "Ref": "2011ApJ...728...95V", "Flag": "1"}, "Gaia Parallax": {"Value": "-", "Error": "-", "Ref": "-", "Flag": "1"}, "D": {"Value": "1.73", "Error": "?", "Ref": "2017ApJ...835...29Y", "Flag": "0"}, "Inclination": {"Value": "65", "Error": "2", "Ref": "2011ApJ...728...95V", "Flag": "1"}, "M1": {"Value": "2.4", "Error": "0.12", "Ref": "2011ApJ...728...95V", "Flag": "1"}, "M2": {"Value": "0.034", "Error": "0.002", "Ref": "2011ApJ...728...95V", "Flag": "1"}, "Tnight": {"Value": "-", "Error": "-", "Ref": "-", "Flag": "1"}, "Heating Efficiency": {"Value": "-", "Error": "-", "Ref": "-", "Flag": "1"}, "Type": {"Value": "BW", "Error": "-", "Ref": "-", "Flag": "1"}, "COMMENTS": {"Value": "We have done it"}, "fm": {"Value": "5.22752337632433e-06", "Error": "1.0545823079581879e-10", "Ref": "Derived", "Flag": 1}, "M1_min": {"Value": "1.7914855772426255", "Error": "0.044876764198603675", "Ref": "Derived", "Flag": 1}, "M2_min": {"Value": "0.025845685754871964", "Error": "0.0005774080219195575", "Ref": "Derived", "Flag": 1}, "q": {"Value": "69.31468540759948", "Error": "0.7854356670025541", "Ref": "Derived", "Flag": 1}}